mysql_module/__init__.py
mysql_module/my_module.py
mysql_module-0.1.1.dist-info/METADATA
mysql_module-0.1.1.dist-info/WHEEL
mysql_module-0.1.1.dist-info/top_level.txt
mysql_module-0.1.1.dist-info/RECORD
