Metadata-Version: 2.1
Name: mysql-module
Version: 0.1.1
Summary: A Python module for interacting with MySQL databases
Author: H-Rasheed
Author-email: rsm878yourkhan@gmail.com
Requires-Dist: mysql-connector-python
